[
  {
    "type": "product",
    "product_id": "P001",
    "product_name": "لابتوب Dell XPS 15",
    "product_barcode": "7001234567890",
    "product_price_retail": 3500000,
    "product_price_wholesale": 3200000,
    "product_cost_retail": 2800000,
    "product_cost_wholesale": 2600000,
    "stock_quantity": 8,
    "min_stock": 3,
    "product_category": "1",
    "supplier": "شركة Dell العراق",
    "timestamp": "2025-11-05T10:00:00.000Z"
  },
  {
    "type": "product",
    "product_id": "P002",
    "product_name": "هاتف iPhone 15 Pro",
    "product_barcode": "7001234567891",
    "product_price_retail": 2800000,
    "product_price_wholesale": 2600000,
    "product_cost_retail": 2200000,
    "product_cost_wholesale": 2000000,
    "stock_quantity": 15,
    "min_stock": 5,
    "product_category": "3",
    "supplier": "موزع Apple المعتمد",
    "timestamp": "2025-11-05T10:05:00.000Z"
  },
  {
    "type": "product",
    "product_id": "P003",
    "product_name": "سماعات Bose QuietComfort 45",
    "product_barcode": "7001234567892",
    "product_price_retail": 180000,
    "product_price_wholesale": 165000,
    "product_cost_retail": 130000,
    "product_cost_wholesale": 120000,
    "stock_quantity": 30,
    "min_stock": 10,
    "product_category": "2",
    "supplier": "شركة الصوتيات الحديثة",
    "timestamp": "2025-11-05T10:10:00.000Z"
  },
  {
    "type": "product",
    "product_id": "P004",
    "product_name": "تابلت iPad Air M2",
    "product_barcode": "7001234567893",
    "product_price_retail": 1500000,
    "product_price_wholesale": 1400000,
    "product_cost_retail": 1150000,
    "product_cost_wholesale": 1050000,
    "stock_quantity": 12,
    "min_stock": 4,
    "product_category": "3",
    "supplier": "موزع Apple المعتمد",
    "timestamp": "2025-11-05T10:15:00.000Z"
  },
  {
    "type": "product",
    "product_id": "P005",
    "product_name": "ماوس Logitech MX Master 3S",
    "product_barcode": "7001234567894",
    "product_price_retail": 85000,
    "product_price_wholesale": 75000,
    "product_cost_retail": 55000,
    "product_cost_wholesale": 50000,
    "stock_quantity": 45,
    "min_stock": 15,
    "product_category": "2",
    "supplier": "شركة لوجيتك العراق",
    "timestamp": "2025-11-05T10:20:00.000Z"
  },
  {
    "type": "product",
    "product_id": "P006",
    "product_name": "كيبورد ميكانيكي Corsair K95",
    "product_barcode": "7001234567895",
    "product_price_retail": 120000,
    "product_price_wholesale": 110000,
    "product_cost_retail": 85000,
    "product_cost_wholesale": 75000,
    "stock_quantity": 20,
    "min_stock": 8,
    "product_category": "2",
    "supplier": "شركة كورسير",
    "timestamp": "2025-11-05T10:25:00.000Z"
  },
  {
    "type": "product",
    "product_id": "P007",
    "product_name": "شاشة Samsung 27 بوصة 4K",
    "product_barcode": "7001234567896",
    "product_price_retail": 450000,
    "product_price_wholesale": 420000,
    "product_cost_retail": 350000,
    "product_cost_wholesale": 320000,
    "stock_quantity": 10,
    "min_stock": 3,
    "product_category": "1",
    "supplier": "موزع سامسونج",
    "timestamp": "2025-11-05T10:30:00.000Z"
  },
  {
    "type": "product",
    "product_id": "P008",
    "product_name": "هاتف Samsung Galaxy S24 Ultra",
    "product_barcode": "7001234567897",
    "product_price_retail": 1800000,
    "product_price_wholesale": 1700000,
    "product_cost_retail": 1400000,
    "product_cost_wholesale": 1300000,
    "stock_quantity": 18,
    "min_stock": 6,
    "product_category": "3",
    "supplier": "موزع سامسونج",
    "timestamp": "2025-11-05T10:35:00.000Z"
  },
  {
    "type": "product",
    "product_id": "P009",
    "product_name": "ساعة Apple Watch Series 9",
    "product_barcode": "7001234567898",
    "product_price_retail": 950000,
    "product_price_wholesale": 900000,
    "product_cost_retail": 750000,
    "product_cost_wholesale": 700000,
    "stock_quantity": 14,
    "min_stock": 5,
    "product_category": "3",
    "supplier": "موزع Apple المعتمد",
    "timestamp": "2025-11-05T10:40:00.000Z"
  },
  {
    "type": "product",
    "product_id": "P010",
    "product_name": "كاميرا Canon EOS R6",
    "product_barcode": "7001234567899",
    "product_price_retail": 4200000,
    "product_price_wholesale": 4000000,
    "product_cost_retail": 3500000,
    "product_cost_wholesale": 3300000,
    "stock_quantity": 5,
    "min_stock": 2,
    "product_category": "1",
    "supplier": "شركة كانون العراق",
    "timestamp": "2025-11-05T10:45:00.000Z"
  },
  {
    "type": "product",
    "product_id": "P011",
    "product_name": "بطارية محمولة Anker 20000mAh",
    "product_barcode": "7001234567900",
    "product_price_retail": 65000,
    "product_price_wholesale": 55000,
    "product_cost_retail": 40000,
    "product_cost_wholesale": 35000,
    "stock_quantity": 60,
    "min_stock": 20,
    "product_category": "2",
    "supplier": "شركة أنكر",
    "timestamp": "2025-11-05T10:50:00.000Z"
  },
  {
    "type": "product",
    "product_id": "P012",
    "product_name": "راوتر TP-Link WiFi 6",
    "product_barcode": "7001234567901",
    "product_price_retail": 95000,
    "product_price_wholesale": 85000,
    "product_cost_retail": 65000,
    "product_cost_wholesale": 55000,
    "stock_quantity": 25,
    "min_stock": 8,
    "product_category": "1",
    "supplier": "شركة TP-Link",
    "timestamp": "2025-11-05T10:55:00.000Z"
  },
  {
    "type": "product",
    "product_id": "P013",
    "product_name": "هارد خارجي Seagate 2TB",
    "product_barcode": "7001234567902",
    "product_price_retail": 110000,
    "product_price_wholesale": 100000,
    "product_cost_retail": 75000,
    "product_cost_wholesale": 65000,
    "stock_quantity": 35,
    "min_stock": 12,
    "product_category": "2",
    "supplier": "موزع Seagate",
    "timestamp": "2025-11-05T11:00:00.000Z"
  },
  {
    "type": "product",
    "product_id": "P014",
    "product_name": "ذاكرة RAM Corsair 32GB DDR5",
    "product_barcode": "7001234567903",
    "product_price_retail": 180000,
    "product_price_wholesale": 165000,
    "product_cost_retail": 135000,
    "product_cost_wholesale": 120000,
    "stock_quantity": 22,
    "min_stock": 8,
    "product_category": "2",
    "supplier": "شركة كورسير",
    "timestamp": "2025-11-05T11:05:00.000Z"
  },
  {
    "type": "product",
    "product_id": "P015",
    "product_name": "لابتوب HP Pavilion Gaming",
    "product_barcode": "7001234567904",
    "product_price_retail": 1800000,
    "product_price_wholesale": 1700000,
    "product_cost_retail": 1450000,
    "product_cost_wholesale": 1350000,
    "stock_quantity": 6,
    "min_stock": 2,
    "product_category": "1",
    "supplier": "شركة HP العراق",
    "timestamp": "2025-11-05T11:10:00.000Z"
  },
  {
    "type": "product",
    "product_id": "P016",
    "product_name": "سماعات AirPods Pro 2",
    "product_barcode": "7001234567905",
    "product_price_retail": 550000,
    "product_price_wholesale": 520000,
    "product_cost_retail": 450000,
    "product_cost_wholesale": 420000,
    "stock_quantity": 28,
    "min_stock": 10,
    "product_category": "2",
    "supplier": "موزع Apple المعتمد",
    "timestamp": "2025-11-05T11:15:00.000Z"
  },
  {
    "type": "product",
    "product_id": "P017",
    "product_name": "معالج AMD Ryzen 9 7950X",
    "product_barcode": "7001234567906",
    "product_price_retail": 950000,
    "product_price_wholesale": 900000,
    "product_cost_retail": 750000,
    "product_cost_wholesale": 700000,
    "stock_quantity": 10,
    "min_stock": 3,
    "product_category": "1",
    "supplier": "موزع AMD",
    "timestamp": "2025-11-05T11:20:00.000Z"
  },
  {
    "type": "product",
    "product_id": "P018",
    "product_name": "كرت شاشة NVIDIA RTX 4070",
    "product_barcode": "7001234567907",
    "product_price_retail": 1500000,
    "product_price_wholesale": 1400000,
    "product_cost_retail": 1200000,
    "product_cost_wholesale": 1100000,
    "stock_quantity": 7,
    "min_stock": 3,
    "product_category": "1",
    "supplier": "موزع NVIDIA",
    "timestamp": "2025-11-05T11:25:00.000Z"
  },
  {
    "type": "product",
    "product_id": "P019",
    "product_name": "طابعة HP LaserJet Pro",
    "product_barcode": "7001234567908",
    "product_price_retail": 380000,
    "product_price_wholesale": 350000,
    "product_cost_retail": 280000,
    "product_cost_wholesale": 250000,
    "stock_quantity": 12,
    "min_stock": 4,
    "product_category": "1",
    "supplier": "شركة HP العراق",
    "timestamp": "2025-11-05T11:30:00.000Z"
  },
  {
    "type": "product",
    "product_id": "P020",
    "product_name": "شاحن سريع Anker 65W",
    "product_barcode": "7001234567909",
    "product_price_retail": 45000,
    "product_price_wholesale": 40000,
    "product_cost_retail": 28000,
    "product_cost_wholesale": 25000,
    "stock_quantity": 80,
    "min_stock": 25,
    "product_category": "2",
    "supplier": "شركة أنكر",
    "timestamp": "2025-11-05T11:35:00.000Z"
  }
]
